{
  "file": "data\\converted\\9 ст.68_ru.txt",
  "language": "ru",
  "triplets_count": 18,
  "triplets": [
    {
      "subject": "Документ",
      "predicate": "упоминает",
      "object": "# Исходный файл: 9 ст.68.docx",
      "confidence": 0.85,
      "language": "ru"
    },
    {
      "subject": "Документ",
      "predicate": "упоминает",
      "object": "# Путь: data\\Солва\\Пров органы пакет документов\\Завления в о",
      "confidence": 0.85,
      "language": "ru"
    },
    {
      "subject": "Документ",
      "predicate": "упоминает",
      "object": "# Размер: 2576 символов",
      "confidence": 0.85,
      "language": "ru"
    },
    {
      "subject": "Документ",
      "predicate": "упоминает",
      "object": "разъяснения требований ст.68 УК РК",
      "confidence": 0.85,
      "language": "ru"
    },
    {
      "subject": "Документ",
      "predicate": "упоминает",
      "object": "г. _____________                                            ",
      "confidence": 0.85,
      "language": "ru"
    },
    {
      "subject": "Документ",
      "predicate": "упоминает",
      "object": "Следователь СО УП города Экибастуза лейтенант полиции Иіс А.",
      "confidence": 0.85,
      "language": "ru"
    },
    {
      "subject": "Документ",
      "predicate": "упоминает",
      "object": "1. Лицо, совершившее проступок или преступление небольшой ил",
      "confidence": 0.85,
      "language": "ru"
    },
    {
      "subject": "Документ",
      "predicate": "упоминает",
      "object": "2. Несовершеннолетний, беременная женщина, женщина, имеющая ",
      "confidence": 0.85,
      "language": "ru"
    },
    {
      "subject": "Документ",
      "predicate": "упоминает",
      "object": "3. В случаях, когда уголовным правонарушением причинен вред ",
      "confidence": 0.85,
      "language": "ru"
    },
    {
      "subject": "Документ",
      "predicate": "упоминает",
      "object": "4. Лицо, может быть освобождено от уголовной ответственности",
      "confidence": 0.85,
      "language": "ru"
    },
    {
      "subject": "Документ",
      "predicate": "упоминает",
      "object": "Согласно п.2 ст.11 УК РК к категории преступлений средней тя",
      "confidence": 0.85,
      "language": "ru"
    },
    {
      "subject": "Документ",
      "predicate": "упоминает",
      "object": "В связи с этим, может быть вынесено постановление о прекраще",
      "confidence": 0.85,
      "language": "ru"
    },
    {
      "subject": "Документ",
      "predicate": "упоминает",
      "object": "Представитель потерпевшего Бойко С.В. ознакомившись с указан",
      "confidence": 0.85,
      "language": "ru"
    },
    {
      "subject": "Документ",
      "predicate": "упоминает",
      "object": "____________________________________________________________",
      "confidence": 0.85,
      "language": "ru"
    },
    {
      "subject": "Документ",
      "predicate": "упоминает",
      "object": "Представитель потерпевшего: ___________________",
      "confidence": 0.85,
      "language": "ru"
    },
    {
      "subject": "Документ",
      "predicate": "упоминает",
      "object": "Протокол составил, права разъяснил:",
      "confidence": 0.85,
      "language": "ru"
    },
    {
      "subject": "Документ",
      "predicate": "упоминает",
      "object": "Следователь СО УП г.Экибастуза",
      "confidence": 0.85,
      "language": "ru"
    },
    {
      "subject": "Документ",
      "predicate": "упоминает",
      "object": "лейтенант полиции\t\t\t                        \t\t              ",
      "confidence": 0.85,
      "language": "ru"
    }
  ],
  "processed_at": "2025-10-26T10:36:36.975194"
}