{
  "file": "data\\converted\\Признание законным представителем (5) - копия.txt",
  "language": "ru",
  "triplets_count": 26,
  "triplets": [
    {
      "subject": "Документ",
      "predicate": "упоминает",
      "object": "# Исходный файл: Признание законным представителем (5) - коп",
      "confidence": 0.85,
      "language": "ru"
    },
    {
      "subject": "Документ",
      "predicate": "упоминает",
      "object": "# Путь: data\\Солва\\Пров органы пакет документов\\Завления в о",
      "confidence": 0.85,
      "language": "ru"
    },
    {
      "subject": "Документ",
      "predicate": "упоминает",
      "object": "# Размер: 7366 символов",
      "confidence": 0.85,
      "language": "ru"
    },
    {
      "subject": "Документ",
      "predicate": "упоминает",
      "object": "П О С Т А Н О В Л Е Н И Е",
      "confidence": 0.85,
      "language": "ru"
    },
    {
      "subject": "Документ",
      "predicate": "упоминает",
      "object": "о признании представителем потерпевшего.",
      "confidence": 0.85,
      "language": "ru"
    },
    {
      "subject": "Документ",
      "predicate": "упоминает",
      "object": "г. Алматы\t                         «10»: «50»\t\t             ",
      "confidence": 0.85,
      "language": "ru"
    },
    {
      "subject": "Документ",
      "predicate": "упоминает",
      "object": "Следователь СО Юго-Восточного ОП УП города Караганды рядовой",
      "confidence": 0.85,
      "language": "ru"
    },
    {
      "subject": "Документ",
      "predicate": "упоминает",
      "object": "В период времени с  года по  года неизвестное лицо, находясь",
      "confidence": 0.85,
      "language": "ru"
    },
    {
      "subject": "Документ",
      "predicate": "упоминает",
      "object": "27.05.2020 года данный факт зарегистрирован в Едином реестре",
      "confidence": 0.85,
      "language": "ru"
    },
    {
      "subject": "Документ",
      "predicate": "упоминает",
      "object": "В ходе досудебного расследования установлено, что ТОО «МФО «",
      "confidence": 0.85,
      "language": "ru"
    },
    {
      "subject": "Документ",
      "predicate": "упоминает",
      "object": "На основании вышеизложенного, руководствуюсь ст.ст.71 ч.12, ",
      "confidence": 0.85,
      "language": "ru"
    },
    {
      "subject": "Документ",
      "predicate": "упоминает",
      "object": "П О С Т А Н О В И Л :",
      "confidence": 0.85,
      "language": "ru"
    },
    {
      "subject": "Документ",
      "predicate": "упоминает",
      "object": "Признать потерпевшим юридическое лицо ТОО «МФО «Creditum», в",
      "confidence": 0.85,
      "language": "ru"
    },
    {
      "subject": "Документ",
      "predicate": "упоминает",
      "object": "О принятом решении уведомить заинтересованных лиц.",
      "confidence": 0.85,
      "language": "ru"
    },
    {
      "subject": "Документ",
      "predicate": "упоминает",
      "object": "Копию настоящего постановления направить прокурору района им",
      "confidence": 0.85,
      "language": "ru"
    },
    {
      "subject": "Документ",
      "predicate": "упоминает",
      "object": "Постановление мне объявлено, одновременно мне разъяснены пра",
      "confidence": 0.85,
      "language": "ru"
    },
    {
      "subject": "Документ",
      "predicate": "упоминает",
      "object": "Представитель ______________________________________________",
      "confidence": 0.85,
      "language": "ru"
    },
    {
      "subject": "Документ",
      "predicate": "упоминает",
      "object": "Согласно ч .6 ст.71 УПК РК о том, 6. Потерпевший имеет право",
      "confidence": 0.85,
      "language": "ru"
    },
    {
      "subject": "Документ",
      "predicate": "упоминает",
      "object": "1) знать о предъявленном подозрении и обвинении; 2) давать п",
      "confidence": 0.85,
      "language": "ru"
    },
    {
      "subject": "Документ",
      "predicate": "упоминает",
      "object": "Согласно ст. 71 УПК РК:",
      "confidence": 0.85,
      "language": "ru"
    },
    {
      "subject": "Документ",
      "predicate": "упоминает",
      "object": "ч. 7. Потерпевший, а в случае его смерти – его правопреемник",
      "confidence": 0.85,
      "language": "ru"
    },
    {
      "subject": "Документ",
      "predicate": "упоминает",
      "object": "______________",
      "confidence": 0.85,
      "language": "ru"
    },
    {
      "subject": "Документ",
      "predicate": "упоминает",
      "object": "Постановление объявил, права разъяснил:",
      "confidence": 0.85,
      "language": "ru"
    },
    {
      "subject": "Документ",
      "predicate": "упоминает",
      "object": "Следователь СО",
      "confidence": 0.85,
      "language": "ru"
    },
    {
      "subject": "Документ",
      "predicate": "упоминает",
      "object": "Юго-Восточного ОП",
      "confidence": 0.85,
      "language": "ru"
    },
    {
      "subject": "Документ",
      "predicate": "упоминает",
      "object": "рядовой полиции \t\t\t\t\t                        Шарипова О.Б.",
      "confidence": 0.85,
      "language": "ru"
    }
  ],
  "processed_at": "2025-10-26T10:36:46.915862"
}